{
    "data": [
        {
            "id": 1,
            "name": "河流a",
            "level": 11,
            "trend": "涨"
        },
        {
            "id": 2,
            "name": "河流b",
            "level": 63.12,
            "trend": "涨"
        },
        {
            "id": 3,
            "name": "河流a",
            "level": 11,
            "trend": "平"
        },
        {
            "id": 4,
            "name": "河流b",
            "level": 63.12,
            "trend": "平"
        },
        {
            "id": 5,
            "name": "河流a",
            "level": 11,
            "trend": "落"
        },
        {
            "id": 6,
            "name": "河流b",
            "level": 63.12,
            "trend": "落"
        }
    ]
}